{
  "key": "solid3d_bluegreen_172",
  "title": "构建以知识为中心的数据底座",
  "source": "010 立体图示模板（蓝绿配色版）.pptx",
  "slide_num": 172,
  "canvas_emu": [
    12192000,
    6858000
  ],
  "shape_count": 91,
  "media": {},
  "charts_unsupported": [],
  "flatten": {
    "colors": 590,
    "colors_unresolved": 0,
    "fonts": 56
  },
  "foreign_rels_stripped": 0,
  "text_slots": [
    {
      "id": 0,
      "text": "知识服务层"
    },
    {
      "id": 1,
      "text": "数智应用层"
    },
    {
      "id": 2,
      "text": "业务逻辑"
    },
    {
      "id": 3,
      "text": "大模型"
    },
    {
      "id": 4,
      "text": "访问控制"
    },
    {
      "id": 5,
      "text": "数据分析"
    },
    {
      "id": 6,
      "text": "加密管理"
    },
    {
      "id": 7,
      "text": "数据保护"
    },
    {
      "id": 8,
      "text": "自助分析"
    },
    {
      "id": 9,
      "text": "知识问答"
    },
    {
      "id": 10,
      "text": "智能决策"
    },
    {
      "id": 11,
      "text": "知识洞察"
    },
    {
      "id": 12,
      "text": "决策流"
    },
    {
      "id": 13,
      "text": "知识抽取"
    },
    {
      "id": 14,
      "text": "知识构建"
    },
    {
      "id": 15,
      "text": "本体建模"
    },
    {
      "id": 16,
      "text": "应用部署"
    },
    {
      "id": 17,
      "text": "数据存储"
    },
    {
      "id": 18,
      "text": "企业流程"
    },
    {
      "id": 19,
      "text": "业务规则"
    },
    {
      "id": 20,
      "text": "业务术语"
    },
    {
      "id": 21,
      "text": "专家经验"
    },
    {
      "id": 22,
      "text": "AI/ML"
    },
    {
      "id": 23,
      "text": "模型"
    },
    {
      "id": 24,
      "text": "异构数据源"
    },
    {
      "id": 25,
      "text": "知识湖"
    },
    {
      "id": 26,
      "text": "数智开发治理层"
    },
    {
      "id": 27,
      "text": "数据源"
    },
    {
      "id": 28,
      "text": "分布式"
    },
    {
      "id": 29,
      "text": "存储层"
    },
    {
      "id": 30,
      "text": "分析层"
    },
    {
      "id": 31,
      "text": "安全性"
    },
    {
      "id": 32,
      "text": "可扩展"
    },
    {
      "id": 33,
      "text": "处理层"
    },
    {
      "id": 34,
      "text": "数据分析"
    },
    {
      "id": 35,
      "text": "数据源"
    },
    {
      "id": 36,
      "text": "构建以知识为中心的数据底座"
    },
    {
      "id": 37,
      "text": "传统安全"
    },
    {
      "id": 38,
      "text": "全局资产难盘清"
    },
    {
      "id": 39,
      "text": "云内资产无感知"
    },
    {
      "id": 40,
      "text": "全局"
    },
    {
      "id": 41,
      "text": "数据"
    },
    {
      "id": 42,
      "text": "难联通"
    },
    {
      "id": 43,
      "text": "云"
    },
    {
      "id": 44,
      "text": "内外"
    },
    {
      "id": 45,
      "text": "数据孤岛"
    },
    {
      "id": 46,
      "text": "威胁"
    },
    {
      "id": 47,
      "text": "分析难"
    },
    {
      "id": 48,
      "text": "精准"
    },
    {
      "id": 49,
      "text": "威胁数据源有限"
    },
    {
      "id": 50,
      "text": "响应处置难协同"
    },
    {
      "id": 51,
      "text": "安全"
    },
    {
      "id": 52,
      "text": "/"
    },
    {
      "id": 53,
      "text": "云资源割裂"
    },
    {
      "id": 54,
      "text": "性能瓶颈难弹性"
    },
    {
      "id": 55,
      "text": "限于软硬件规格"
    },
    {
      "id": 56,
      "text": "云原生安全"
    },
    {
      "id": 57,
      "text": "资产"
    },
    {
      "id": 58,
      "text": "&"
    },
    {
      "id": 59,
      "text": "安全一体化"
    },
    {
      "id": 60,
      "text": "资产变动秒级感知"
    },
    {
      "id": 61,
      "text": "云内数据无缝对接"
    },
    {
      "id": 62,
      "text": "OBS/RDS…PB"
    },
    {
      "id": 63,
      "text": "级性能"
    },
    {
      "id": 64,
      "text": "威胁分析数据源广"
    },
    {
      "id": 65,
      "text": "50+"
    },
    {
      "id": 66,
      "text": "云日志"
    },
    {
      "id": 67,
      "text": "/200+"
    },
    {
      "id": 68,
      "text": "安全日志"
    },
    {
      "id": 69,
      "text": "自动协同编排与响应"
    },
    {
      "id": 70,
      "text": "400+"
    },
    {
      "id": 71,
      "text": "模型、"
    },
    {
      "id": 72,
      "text": "100+"
    },
    {
      "id": 73,
      "text": "剧本"
    },
    {
      "id": 74,
      "text": "安全性能弹性扩展"
    },
    {
      "id": 75,
      "text": "分钟级、性能无上限"
    }
  ],
  "summary": ""
}
