{
  "key": "solid3d_bluegreen_144",
  "title": "商业操作系统",
  "source": "010 立体图示模板（蓝绿配色版）.pptx",
  "slide_num": 144,
  "canvas_emu": [
    12192000,
    6858000
  ],
  "shape_count": 71,
  "media": {},
  "charts_unsupported": [],
  "flatten": {
    "colors": 654,
    "colors_unresolved": 0,
    "fonts": 120
  },
  "foreign_rels_stripped": 0,
  "text_slots": [
    {
      "id": 0,
      "text": "商业操作系统"
    },
    {
      "id": 1,
      "text": "云"
    },
    {
      "id": 2,
      "text": "平台"
    },
    {
      "id": 3,
      "text": "保护层"
    },
    {
      "id": 4,
      "text": "提效"
    },
    {
      "id": 5,
      "text": "层"
    },
    {
      "id": 6,
      "text": "机器提效"
    },
    {
      "id": 7,
      "text": "多模态"
    },
    {
      "id": 8,
      "text": "融合"
    },
    {
      "id": 9,
      "text": "无监督、自监督训练"
    },
    {
      "id": 10,
      "text": "提效人力技术"
    },
    {
      "id": 11,
      "text": "模型"
    },
    {
      "id": 12,
      "text": "样本"
    },
    {
      "id": 13,
      "text": "聚类"
    },
    {
      "id": 14,
      "text": "人员"
    },
    {
      "id": 15,
      "text": "画像"
    },
    {
      "id": 16,
      "text": "噪声识别"
    },
    {
      "id": 17,
      "text": "主动学习"
    },
    {
      "id": 18,
      "text": "智能分发"
    },
    {
      "id": 19,
      "text": "多任务学习"
    },
    {
      "id": 20,
      "text": "模型"
    },
    {
      "id": 21,
      "text": "源码保护"
    },
    {
      "id": 22,
      "text": "对抗样本防御"
    },
    {
      "id": 23,
      "text": "漏洞挖掘"
    },
    {
      "id": 24,
      "text": "系统安全"
    },
    {
      "id": 25,
      "text": "恶意流量清洗平台"
    },
    {
      "id": 26,
      "text": "全生命周期漏洞防控"
    },
    {
      "id": 27,
      "text": "百万级云负载反入侵体系"
    },
    {
      "id": 28,
      "text": "数据安全"
    },
    {
      "id": 29,
      "text": "数据可用不可用"
    },
    {
      "id": 30,
      "text": "账号认证"
    },
    {
      "id": 31,
      "text": "全链路数据保护"
    },
    {
      "id": 32,
      "text": "业务安全"
    },
    {
      "id": 33,
      "text": "智能风控引擎"
    },
    {
      "id": 34,
      "text": "精准识别黑灰"
    },
    {
      "id": 35,
      "text": "实人认证"
    },
    {
      "id": 36,
      "text": "平台治理"
    },
    {
      "id": 37,
      "text": "知识保护科技大脑"
    },
    {
      "id": 38,
      "text": "营商保"
    },
    {
      "id": 39,
      "text": "实人认证"
    },
    {
      "id": 40,
      "text": "认知区"
    },
    {
      "id": 41,
      "text": "文本安全"
    },
    {
      "id": 42,
      "text": "情感分析"
    },
    {
      "id": 43,
      "text": "文本对抗"
    },
    {
      "id": 44,
      "text": "感知区"
    },
    {
      "id": 45,
      "text": "图像识别"
    },
    {
      "id": 46,
      "text": "文字识别"
    },
    {
      "id": 47,
      "text": "图像对抗"
    },
    {
      "id": 48,
      "text": "生物特征识别"
    },
    {
      "id": 49,
      "text": "视频分析"
    },
    {
      "id": 50,
      "text": "决策区"
    },
    {
      "id": 51,
      "text": "账号行为"
    },
    {
      "id": 52,
      "text": "关联分析"
    },
    {
      "id": 53,
      "text": "安全知识图谱"
    },
    {
      "id": 54,
      "text": "违禁识别"
    },
    {
      "id": 55,
      "text": "内容安全"
    },
    {
      "id": 56,
      "text": "黑客攻击"
    },
    {
      "id": 57,
      "text": "羊毛党"
    },
    {
      "id": 58,
      "text": "机器行为"
    },
    {
      "id": 59,
      "text": "Ddos"
    },
    {
      "id": 60,
      "text": "攻击"
    },
    {
      "id": 61,
      "text": "垃圾信息"
    },
    {
      "id": 62,
      "text": "爬虫"
    },
    {
      "id": 63,
      "text": "原创垃圾"
    },
    {
      "id": 64,
      "text": "漏洞挖掘"
    }
  ],
  "summary": ""
}
